texclean/__init__.py
texclean/texclean.py
texclean-1.0.0.dist-info/metadata.json
texclean-1.0.0.dist-info/WHEEL
texclean-1.0.0.dist-info/RECORD
texclean-1.0.0.dist-info/pbr.json
texclean-1.0.0.dist-info/DESCRIPTION.rst
texclean-1.0.0.dist-info/METADATA
texclean-1.0.0.dist-info/entry_points.txt
texclean-1.0.0.dist-info/top_level.txt
