Metadata-Version: 2.0
Name: texclean
Version: 1.0.0
Summary: Ein Skript zum löschen von temporären Daten in TeX-Projekten.
Home-page: https://gist.github.com/JonasGroeger/8897946
Author: Jonas Gröger
Author-email: jonas.groeger@gmail.com
License: MIT
Keywords: tex latex xelatex lualatex pdflatex
Platform: UNKNOWN
Classifier: Development Status :: 4 - Beta
Classifier: Environment :: Console
Classifier: Intended Audience :: Developers
Classifier: License :: OSI Approved :: MIT License
Classifier: Programming Language :: Python :: 2
Classifier: Programming Language :: Python :: 3
Classifier: Topic :: Utilities
